bigquantdai/__init__.py
bigquantdai/_client.py
bigquantdai/_constant.py
bigquantdai/dai.py
bigquantdai/user_storage.py
bigquantdai-1.0.9.dist-info/METADATA
bigquantdai-1.0.9.dist-info/WHEEL
bigquantdai-1.0.9.dist-info/top_level.txt
bigquantdai-1.0.9.dist-info/RECORD
