Metadata-Version: 2.1
Name: bigquantdai
Version: 1.0.9
Summary: bigquant 数据SDK
Home-page: https://bigquant.com
Author: BigQuant
Author-email: bigquant@bigquant.com
License: MIT
Project-URL: Documentation, https://bigquant.com/wiki/doc/sdk-gMEOV2bGYi
Keywords: 数据SDK,dai,bigquant
Classifier: Development Status :: 4 - Beta
Classifier: Intended Audience :: Developers
Classifier: Topic :: Software Development :: Libraries :: Python Modules
Classifier: License :: OSI Approved :: MIT License
Classifier: Operating System :: OS Independent
Classifier: Programming Language :: Python :: 3
Classifier: Programming Language :: Python :: 3.8
Classifier: Programming Language :: Python :: 3.9
Classifier: Programming Language :: Python :: 3.10
Classifier: Programming Language :: Python :: 3.11
Classifier: Programming Language :: Python :: 3.12
Requires-Python: >=3.8
Requires-Dist: pandas
Requires-Dist: pyarrow
